de05bb265ced687e4baf__mypyc.cpython-314-x86_64-linux-gnu.so
reprospect/__init__.py
reprospect/py.typed
reprospect/installers/cuda_bindings.py
reprospect/installers/nsight_systems.py
reprospect/test/__init__.py
reprospect/test/case.py
reprospect/test/cmake.py
reprospect/test/environment.py
reprospect/test/features.cpython-314-x86_64-linux-gnu.so
reprospect/test/features.py
reprospect/test/sass/__init__.py
reprospect/test/sass/composite.cpython-314-x86_64-linux-gnu.so
reprospect/test/sass/composite.py
reprospect/test/sass/composite_impl.cpython-314-x86_64-linux-gnu.so
reprospect/test/sass/composite_impl.py
reprospect/test/sass/controlflow/__init__.py
reprospect/test/sass/controlflow/block.cpython-314-x86_64-linux-gnu.so
reprospect/test/sass/controlflow/block.py
reprospect/test/sass/instruction/__init__.py
reprospect/test/sass/instruction/address.cpython-314-x86_64-linux-gnu.so
reprospect/test/sass/instruction/address.py
reprospect/test/sass/instruction/atomic.cpython-314-x86_64-linux-gnu.so
reprospect/test/sass/instruction/atomic.py
reprospect/test/sass/instruction/branch.cpython-314-x86_64-linux-gnu.so
reprospect/test/sass/instruction/branch.py
reprospect/test/sass/instruction/constant.cpython-314-x86_64-linux-gnu.so
reprospect/test/sass/instruction/constant.py
reprospect/test/sass/instruction/floating.cpython-314-x86_64-linux-gnu.so
reprospect/test/sass/instruction/floating.py
reprospect/test/sass/instruction/half.cpython-314-x86_64-linux-gnu.so
reprospect/test/sass/instruction/half.py
reprospect/test/sass/instruction/immediate.py
reprospect/test/sass/instruction/instruction.cpython-314-x86_64-linux-gnu.so
reprospect/test/sass/instruction/instruction.py
reprospect/test/sass/instruction/integer.cpython-314-x86_64-linux-gnu.so
reprospect/test/sass/instruction/integer.py
reprospect/test/sass/instruction/load.cpython-314-x86_64-linux-gnu.so
reprospect/test/sass/instruction/load.py
reprospect-1.0.2.dist-info/METADATA
reprospect-1.0.2.dist-info/WHEEL
reprospect-1.0.2.dist-info/entry_points.txt
reprospect-1.0.2.dist-info/top_level.txt
reprospect-1.0.2.dist-info/RECORD
reprospect-1.0.2.dist-info/licenses/LICENSE
