Metadata-Version: 2.4
Name: reprospect
Version: 1.0.2
Summary: A framework for reproducible prospecting of CUDA applications.
Author: Arnst Maarten, Tomasetti Romin
License-Expression: LGPL-3.0-only
Project-URL: Homepage, https://github.com/uliegecsm/reprospect
Project-URL: Documentation, https://uliegecsm.github.io/reprospect/
Requires-Python: >=3.10
License-File: LICENSE
Requires-Dist: attrs
Requires-Dist: backports.strenum
Requires-Dist: blake3
Requires-Dist: cmake-file-api==0.0.8.6
Requires-Dist: ijson
Requires-Dist: mypy_extensions
Requires-Dist: pandas
Requires-Dist: pyelftools==0.32
Requires-Dist: regex
Requires-Dist: rich
Requires-Dist: rich-tools
Requires-Dist: semantic_version
Requires-Dist: system-helpers>=0.0.3
Requires-Dist: typing-extensions>=4.4.0
Dynamic: license-file
